{"nodes": [{"id": "apps_web_index_ui_directions_entrypoint", "label": "UI Directions Browser Entrypoint", "file_type": "document", "source_file": "apps/web/index.html", "source_location": null, "source_url": null, "captured_at": null, "author": null, "contributor": null}], "edges": [{"source": "apps_web_index_ui_directions_entrypoint", "target": "docs_decisions_0002_ui_directions_meridian", "relation": "conceptually_related_to", "confidence": "INFERRED", "confidence_score": 0.75, "source_file": "apps/web/index.html", "source_location": null, "weight": 1.0}], "hyperedges": []}